odoo10_addon_project_task_category-10.0.1.1.0-py2.7-nspkg.pth
odoo/addons/project_task_category/README.rst
odoo/addons/project_task_category/__init__.py
odoo/addons/project_task_category/__manifest__.py
odoo/addons/project_task_category/data/project_data.xml
odoo/addons/project_task_category/models/__init__.py
odoo/addons/project_task_category/models/project_category.py
odoo/addons/project_task_category/models/project_task.py
odoo/addons/project_task_category/security/ir.model.access.csv
odoo/addons/project_task_category/views/project_categ_view.xml
odoo/addons/project_task_category/views/project_task_view.xml
odoo10_addon_project_task_category-10.0.1.1.0.dist-info/DESCRIPTION.rst
odoo10_addon_project_task_category-10.0.1.1.0.dist-info/METADATA
odoo10_addon_project_task_category-10.0.1.1.0.dist-info/RECORD
odoo10_addon_project_task_category-10.0.1.1.0.dist-info/WHEEL
odoo10_addon_project_task_category-10.0.1.1.0.dist-info/metadata.json
odoo10_addon_project_task_category-10.0.1.1.0.dist-info/namespace_packages.txt
odoo10_addon_project_task_category-10.0.1.1.0.dist-info/top_level.txt
